sphinx_multitoc_numbering/__init__.py
sphinx_multitoc_numbering-0.1.3.dist-info/LICENSE
sphinx_multitoc_numbering-0.1.3.dist-info/METADATA
sphinx_multitoc_numbering-0.1.3.dist-info/WHEEL
sphinx_multitoc_numbering-0.1.3.dist-info/top_level.txt
sphinx_multitoc_numbering-0.1.3.dist-info/RECORD
