Metadata-Version: 2.1
Name: sphinx-multitoc-numbering
Version: 0.1.3
Summary: Supporting continuous HTML section numbering
Home-page: UNKNOWN
License: MIT
Platform: UNKNOWN
Provides-Extra: code_style
Provides-Extra: testing
Provides-Extra: rtd
